{
  "sm": [
    {
      "w": 6,
      "h": 23,
      "x": 1,
      "y": 0,
      "i": "992",
      "moved": false,
      "static": false
    },
    {
      "w": 1,
      "h": 1,
      "x": 0,
      "y": 0,
      "i": "991",
      "moved": false,
      "static": false
    },
    {
      "w": 1,
      "h": 1,
      "x": 0,
      "y": 1,
      "i": "997",
      "moved": false,
      "static": false
    },
    {
      "w": 1,
      "h": 1,
      "x": 0,
      "y": 2,
      "i": "996",
      "moved": false,
      "static": false
    },
    {
      "w": 1,
      "h": 1,
      "x": 0,
      "y": 3,
      "i": "994",
      "moved": false,
      "static": false
    },
    {
      "w": 1,
      "h": 1,
      "x": 0,
      "y": 4,
      "i": "993",
      "moved": false,
      "static": false
    },
    {
      "w": 1,
      "h": 1,
      "x": 0,
      "y": 5,
      "i": "995",
      "moved": false,
      "static": false
    },
    {
      "w": 4,
      "h": 10,
      "x": 8,
      "y": 0,
      "i": "990",
      "moved": false,
      "static": false
    },
    {
      "w": 1,
      "h": 1,
      "x": 0,
      "y": 6,
      "i": "988",
      "moved": false,
      "static": false
    },
    {
      "w": 1,
      "h": 1,
      "x": 0,
      "y": 7,
      "i": "987",
      "moved": false,
      "static": false
    },
    {
      "w": 1,
      "h": 1,
      "x": 0,
      "y": 8,
      "i": "989",
      "moved": false,
      "static": false
    },
    {
      "w": 1,
      "h": 1,
      "x": 0,
      "y": 9,
      "i": "998",
      "moved": false,
      "static": false
    },
    {
      "w": 1,
      "h": 1,
      "x": 0,
      "y": 10,
      "i": "986",
      "moved": false,
      "static": false
    }
  ],
  "xs": [
    {
      "x": 0,
      "y": 0,
      "w": 2,
      "h": 3,
      "i": "0",
      "resizeHandles": [
        "s",
        "w",
        "e",
        "n",
        "sw",
        "nw",
        "se",
        "ne"
      ]
    },
    {
      "x": 2,
      "y": 0,
      "w": 2,
      "h": 5,
      "i": "1",
      "resizeHandles": [
        "s",
        "w",
        "e",
        "n",
        "sw",
        "nw",
        "se",
        "ne"
      ]
    },
    {
      "x": 4,
      "y": 0,
      "w": 2,
      "h": 2,
      "i": "2",
      "resizeHandles": [
        "s",
        "w",
        "e",
        "n",
        "sw",
        "nw",
        "se",
        "ne"
      ]
    },
    {
      "x": 6,
      "y": 0,
      "w": 2,
      "h": 2,
      "i": "3",
      "resizeHandles": [
        "s",
        "w",
        "e",
        "n",
        "sw",
        "nw",
        "se",
        "ne"
      ]
    },
    {
      "x": 8,
      "y": 0,
      "w": 2,
      "h": 4,
      "i": "4",
      "resizeHandles": [
        "s",
        "w",
        "e",
        "n",
        "sw",
        "nw",
        "se",
        "ne"
      ]
    },
    {
      "x": 10,
      "y": 0,
      "w": 2,
      "h": 4,
      "i": "5",
      "resizeHandles": [
        "s",
        "w",
        "e",
        "n",
        "sw",
        "nw",
        "se",
        "ne"
      ]
    },
    {
      "x": 0,
      "y": 5,
      "w": 2,
      "h": 5,
      "i": "6",
      "resizeHandles": [
        "s",
        "w",
        "e",
        "n",
        "sw",
        "nw",
        "se",
        "ne"
      ]
    },
    {
      "x": 2,
      "y": 2,
      "w": 2,
      "h": 2,
      "i": "7",
      "resizeHandles": [
        "s",
        "w",
        "e",
        "n",
        "sw",
        "nw",
        "se",
        "ne"
      ]
    },
    {
      "x": 4,
      "y": 4,
      "w": 2,
      "h": 4,
      "i": "8",
      "resizeHandles": [
        "s",
        "w",
        "e",
        "n",
        "sw",
        "nw",
        "se",
        "ne"
      ]
    },
    {
      "x": 6,
      "y": 3,
      "w": 2,
      "h": 3,
      "i": "9",
      "resizeHandles": [
        "s",
        "w",
        "e",
        "n",
        "sw",
        "nw",
        "se",
        "ne"
      ]
    },
    {
      "x": 8,
      "y": 4,
      "w": 2,
      "h": 4,
      "i": "10",
      "resizeHandles": [
        "s",
        "w",
        "e",
        "n",
        "sw",
        "nw",
        "se",
        "ne"
      ]
    },
    {
      "x": 10,
      "y": 3,
      "w": 2,
      "h": 3,
      "i": "11",
      "resizeHandles": [
        "s",
        "w",
        "e",
        "n",
        "sw",
        "nw",
        "se",
        "ne"
      ]
    },
    {
      "x": 0,
      "y": 8,
      "w": 2,
      "h": 4,
      "i": "12",
      "resizeHandles": [
        "s",
        "w",
        "e",
        "n",
        "sw",
        "nw",
        "se",
        "ne"
      ]
    }
  ],
  "xxs": [
    {
      "x": 0,
      "y": 0,
      "w": 2,
      "h": 4,
      "i": "0",
      "resizeHandles": [
        "s",
        "w",
        "e",
        "n",
        "sw",
        "nw",
        "se",
        "ne"
      ]
    },
    {
      "x": 2,
      "y": 0,
      "w": 2,
      "h": 4,
      "i": "1",
      "resizeHandles": [
        "s",
        "w",
        "e",
        "n",
        "sw",
        "nw",
        "se",
        "ne"
      ]
    },
    {
      "x": 4,
      "y": 0,
      "w": 2,
      "h": 2,
      "i": "2",
      "resizeHandles": [
        "s",
        "w",
        "e",
        "n",
        "sw",
        "nw",
        "se",
        "ne"
      ]
    },
    {
      "x": 6,
      "y": 0,
      "w": 2,
      "h": 2,
      "i": "3",
      "resizeHandles": [
        "s",
        "w",
        "e",
        "n",
        "sw",
        "nw",
        "se",
        "ne"
      ]
    },
    {
      "x": 8,
      "y": 0,
      "w": 2,
      "h": 5,
      "i": "4",
      "resizeHandles": [
        "s",
        "w",
        "e",
        "n",
        "sw",
        "nw",
        "se",
        "ne"
      ]
    },
    {
      "x": 10,
      "y": 0,
      "w": 2,
      "h": 2,
      "i": "5",
      "resizeHandles": [
        "s",
        "w",
        "e",
        "n",
        "sw",
        "nw",
        "se",
        "ne"
      ]
    },
    {
      "x": 0,
      "y": 2,
      "w": 2,
      "h": 2,
      "i": "6",
      "resizeHandles": [
        "s",
        "w",
        "e",
        "n",
        "sw",
        "nw",
        "se",
        "ne"
      ]
    },
    {
      "x": 2,
      "y": 5,
      "w": 2,
      "h": 5,
      "i": "7",
      "resizeHandles": [
        "s",
        "w",
        "e",
        "n",
        "sw",
        "nw",
        "se",
        "ne"
      ]
    },
    {
      "x": 4,
      "y": 5,
      "w": 2,
      "h": 5,
      "i": "8",
      "resizeHandles": [
        "s",
        "w",
        "e",
        "n",
        "sw",
        "nw",
        "se",
        "ne"
      ]
    },
    {
      "x": 6,
      "y": 3,
      "w": 2,
      "h": 3,
      "i": "9",
      "resizeHandles": [
        "s",
        "w",
        "e",
        "n",
        "sw",
        "nw",
        "se",
        "ne"
      ]
    },
    {
      "x": 8,
      "y": 4,
      "w": 2,
      "h": 4,
      "i": "10",
      "resizeHandles": [
        "s",
        "w",
        "e",
        "n",
        "sw",
        "nw",
        "se",
        "ne"
      ]
    },
    {
      "x": 10,
      "y": 2,
      "w": 2,
      "h": 2,
      "i": "11",
      "resizeHandles": [
        "s",
        "w",
        "e",
        "n",
        "sw",
        "nw",
        "se",
        "ne"
      ]
    },
    {
      "x": 0,
      "y": 6,
      "w": 2,
      "h": 3,
      "i": "12",
      "resizeHandles": [
        "s",
        "w",
        "e",
        "n",
        "sw",
        "nw",
        "se",
        "ne"
      ]
    }
  ]
}